{
  "@context": "https://schema.org",
  "@type": "FAQPage",
  "name": "How's fault decided in Idaho work slip cases?",
  "description": "Comp ignores fault; suits use % negligence.[1]",
  "url": "https://justworkcomplaw.com//faq/general-how-s-fault-decided-in-idaho-work-slip-cases-65",
  "mainEntity": [
    {
      "@type": "Question",
      "name": "How's fault decided in Idaho work slip cases?",
      "acceptedAnswer": {
        "@type": "Answer",
        "text": "Comp ignores fault; suits use % negligence.[1]",
        "description": "**Irrelevant for workers' comp; employer liable via insurance.** Third-party: jury assigns % under modified comparative (barred if >50%).[1][6] Evidence like ignored warnings factors in. No-fault protects you usually."
      }
    }
  ]
}